<annotation verified="yes">
	<folder>img_check</folder>
	<filename>additional_shta_7m_54.jpeg</filename>
	<path>C:\Users\MAFirsov\Documents\github_repo_foto\torpedonosec80-object_foto_dataset-e206c86\dataset_foto_boxes_check\img_check\additional_shta_7m_54.jpeg</path>
	<source>
		<database>Unknown</database>
	</source>
	<size>
		<width>960</width>
		<height>1280</height>
		<depth>3</depth>
	</size>
	<segmented>0</segmented>
	<object>
		<name>shta-7m</name>
		<pose>Unspecified</pose>
		<truncated>0</truncated>
		<difficult>0</difficult>
		<bndbox>
			<xmin>334</xmin>
			<ymin>344</ymin>
			<xmax>770</xmax>
			<ymax>639</ymax>
		</bndbox>
	</object>
</annotation>
