{
    "filename": "image_images_0159.jpg",
    "size": 1446249,
    "regions": [
        {
            "shape_attributes": {
                "name": "polygon",
                "all_points_x": [
                    875,
                    879,
                    909,
                    1326,
                    1365,
                    1344
                ],
                "all_points_y": [
                    474,
                    797,
                    941,
                    936,
                    791,
                    469
                ]
            },
            "region_attributes": {
                "name": "shta-9m",
                "pose": "unspecified",
                "truncated": false,
                "difficult": false
            }
        }
    ]
}