{
    "filename": "image_images_0262.jpg",
    "size": 140518,
    "regions": [
        {
            "shape_attributes": {
                "name": "polygon",
                "all_points_x": [
                    94,
                    35,
                    174,
                    812,
                    969,
                    792
                ],
                "all_points_y": [
                    47,
                    108,
                    717,
                    601,
                    105,
                    53
                ]
            },
            "region_attributes": {
                "name": "shta-3",
                "pose": "frontal",
                "truncated": false,
                "difficult": false
            }
        }
    ]
}