{
    "filename": "image_images_0155.jpg",
    "size": 1592967,
    "regions": [
        {
            "shape_attributes": {
                "name": "polygon",
                "all_points_x": [
                    1046,
                    1042,
                    1056,
                    1391,
                    1447,
                    1440
                ],
                "all_points_y": [
                    732,
                    1007,
                    1109,
                    1141,
                    1039,
                    746
                ]
            },
            "region_attributes": {
                "name": "shta-9m",
                "pose": "frontal",
                "truncated": false,
                "difficult": true
            }
        }
    ]
}